lupulo/inotify_observer.py
lupulo/layout_manager.py
lupulo/exceptions.py
lupulo/http.py
lupulo/startup.tac
lupulo/sse_client.py
lupulo/root.py
lupulo/sse_resource.py
lupulo/listeners_manager.py
lupulo/__init__.py
lupulo/data_schema_manager.py
lupulo/settings.py
lupulo/descriptors/dict.py
lupulo/descriptors/__init__.py
lupulo/descriptors/list.py
lupulo/descriptors/enum.py
lupulo/descriptors/date.py
lupulo/descriptors/number.py
lupulo/listeners/serial_listener.py
lupulo/listeners/mock_listener.py
lupulo/listeners/__init__.py
lupulo/tests/__init__.py
lupulo/tests/backend/test_inotify.py
lupulo/tests/backend/test_data_schema_descriptor.py
lupulo/tests/backend/test_data_schema_generator.py
lupulo/tests/backend/test_sse_client.py
lupulo/tests/backend/__init__.py
lupulo/tests/backend/test_data_schema_validator.py
lupulo/tests/backend/test_listener_manager.py
lupulo/tests/backend/test_url.py
lupulo/tests/backend/benchmarking.py
lupulo/tests/backend/test_layout_manager.py
lupulo/tests/backend/test_web_server.py
lupulo/tests/backend/urls/no_urlpatterns.py
lupulo/tests/backend/urls/gaps_urls.py
lupulo/tests/backend/urls/simple_url.py
lupulo/tests/backend/urls/repeated_url.py
lupulo/tests/backend/urls/__init__.py
lupulo/tests/backend/urls/template_resource.py
lupulo/tests/backend/urls/invalid_resource.py
lupulo/tests/backend/urls/siblings_urls.py
lupulo/tests/backend/urls/dictionary_url.py
lupulo/tests/frontend/accessors.html
lupulo/defaults/data_schema.json
lupulo/defaults/default_urls.py
lupulo/defaults/default_settings.py
lupulo/defaults/layout.json
lupulo/defaults/templates/index.html
lupulo/defaults/templates/debug.html
lupulo/defaults/static/css/main.css
lupulo/templates/benchmarking.html
lupulo/templates/base.html
lupulo/templates/base_debug.html
lupulo/templates/errors/500.html
lupulo/templates/errors/404.html
lupulo/static/js/debug.js
lupulo/static/js/widget.js
lupulo/static/js/accessors.js
lupulo-0.3.dist-info/metadata.json
lupulo-0.3.dist-info/top_level.txt
lupulo-0.3.dist-info/WHEEL
lupulo-0.3.dist-info/RECORD
lupulo-0.3.dist-info/DESCRIPTION.rst
lupulo-0.3.dist-info/METADATA
