Metadata-Version: 2.0
Name: lupulo
Version: 0.3
Summary: Framework to build realtime web pages dedicated to monitor                    robots or IoT devices.
Home-page: http://github.com/kudrom/lupulo
Author: kudrom
Author-email: kudrom@riseup.net
License: GPL
Keywords: lupulo IoT realtime
Platform: UNKNOWN
Classifier: Development Status :: 3 - Alpha
Classifier: Environment :: Web Environment
Classifier: Framework :: Twisted
Classifier: Framework :: Sphinx
Classifier: Intended Audience :: Developers
Classifier: License :: OSI Approved :: GNU General Public License (GPL)
Classifier: Natural Language :: English
Classifier: Operating System :: POSIX :: Linux
Classifier: Programming Language :: JavaScript
Classifier: Programming Language :: Python :: 2
Classifier: Topic :: Software Development :: Libraries :: Application Frameworks
Classifier: Topic :: Software Development :: Embedded Systems
Requires-Dist: pyserial
Requires-Dist: twisted
Requires-Dist: pymongo
Requires-Dist: termcolor
Requires-Dist: jinja2
